{
  "type": "Program",
  "start": 0,
  "end": 750,
  "loc": {
    "start": {
      "line": 1,
      "column": 0
    },
    "end": {
      "line": 41,
      "column": 0
    }
  },
  "sourceType": "module",
  "body": [
    {
      "type": "ImportDeclaration",
      "start": 0,
      "end": 43,
      "loc": {
        "start": {
          "line": 1,
          "column": 0
        },
        "end": {
          "line": 3,
          "column": 15
        }
      },
      "specifiers": [
        {
          "type": "ImportDefaultSpecifier",
          "start": 7,
          "end": 12,
          "loc": {
            "start": {
              "line": 1,
              "column": 7
            },
            "end": {
              "line": 1,
              "column": 12
            }
          },
          "local": {
            "type": "Identifier",
            "start": 7,
            "end": 12,
            "loc": {
              "start": {
                "line": 1,
                "column": 7
              },
              "end": {
                "line": 1,
                "column": 12
              }
            },
            "name": "React"
          }
        },
        {
          "type": "ImportSpecifier",
          "start": 18,
          "end": 27,
          "loc": {
            "start": {
              "line": 2,
              "column": 2
            },
            "end": {
              "line": 2,
              "column": 11
            }
          },
          "imported": {
            "type": "Identifier",
            "start": 18,
            "end": 27,
            "loc": {
              "start": {
                "line": 2,
                "column": 2
              },
              "end": {
                "line": 2,
                "column": 11
              }
            },
            "name": "PropTypes"
          },
          "local": {
            "type": "Identifier",
            "start": 18,
            "end": 27,
            "loc": {
              "start": {
                "line": 2,
                "column": 2
              },
              "end": {
                "line": 2,
                "column": 11
              }
            },
            "name": "PropTypes"
          }
        }
      ],
      "importKind": "value",
      "source": {
        "type": "Literal",
        "start": 35,
        "end": 42,
        "loc": {
          "start": {
            "line": 3,
            "column": 7
          },
          "end": {
            "line": 3,
            "column": 14
          }
        },
        "value": "react",
        "rawValue": "react",
        "raw": "'react'"
      }
    },
    {
      "type": "ImportDeclaration",
      "start": 44,
      "end": 80,
      "loc": {
        "start": {
          "line": 4,
          "column": 0
        },
        "end": {
          "line": 4,
          "column": 36
        }
      },
      "specifiers": [
        {
          "type": "ImportSpecifier",
          "start": 52,
          "end": 62,
          "loc": {
            "start": {
              "line": 4,
              "column": 8
            },
            "end": {
              "line": 4,
              "column": 18
            }
          },
          "imported": {
            "type": "Identifier",
            "start": 52,
            "end": 62,
            "loc": {
              "start": {
                "line": 4,
                "column": 8
              },
              "end": {
                "line": 4,
                "column": 18
              }
            },
            "name": "classNames"
          },
          "local": {
            "type": "Identifier",
            "start": 52,
            "end": 62,
            "loc": {
              "start": {
                "line": 4,
                "column": 8
              },
              "end": {
                "line": 4,
                "column": 18
              }
            },
            "name": "classNames"
          }
        }
      ],
      "importKind": "value",
      "source": {
        "type": "Literal",
        "start": 69,
        "end": 79,
        "loc": {
          "start": {
            "line": 4,
            "column": 25
          },
          "end": {
            "line": 4,
            "column": 35
          }
        },
        "value": "../utils",
        "rawValue": "../utils",
        "raw": "'../utils'"
      },
      "trailingComments": [
        {
          "type": "Block",
          "value": "*\n * 自定义 Icon\n * @param {object} props 传入组件的属性\n * @property {string} props.size 大小\n * @property {string} props.className 自定义 class\n ",
          "start": 82,
          "end": 218,
          "loc": {
            "start": {
              "line": 6,
              "column": 0
            },
            "end": {
              "line": 11,
              "column": 3
            }
          },
          "range": [
            82,
            218
          ]
        }
      ]
    },
    {
      "type": "ExportDefaultDeclaration",
      "start": 219,
      "end": 521,
      "loc": {
        "start": {
          "line": 12,
          "column": 0
        },
        "end": {
          "line": 24,
          "column": 1
        }
      },
      "declaration": {
        "type": "FunctionDeclaration",
        "start": 234,
        "end": 521,
        "loc": {
          "start": {
            "line": 12,
            "column": 15
          },
          "end": {
            "line": 24,
            "column": 1
          }
        },
        "id": {
          "type": "Identifier",
          "start": 243,
          "end": 252,
          "loc": {
            "start": {
              "line": 12,
              "column": 24
            },
            "end": {
              "line": 12,
              "column": 33
            }
          },
          "name": "IconCheck",
          "leadingComments": null
        },
        "generator": false,
        "expression": false,
        "async": false,
        "params": [
          {
            "type": "Identifier",
            "start": 253,
            "end": 258,
            "loc": {
              "start": {
                "line": 12,
                "column": 34
              },
              "end": {
                "line": 12,
                "column": 39
              }
            },
            "name": "props"
          }
        ],
        "body": {
          "type": "BlockStatement",
          "start": 260,
          "end": 521,
          "loc": {
            "start": {
              "line": 12,
              "column": 41
            },
            "end": {
              "line": 24,
              "column": 1
            }
          },
          "body": [
            {
              "type": "VariableDeclaration",
              "start": 264,
              "end": 307,
              "loc": {
                "start": {
                  "line": 13,
                  "column": 2
                },
                "end": {
                  "line": 13,
                  "column": 45
                }
              },
              "declarations": [
                {
                  "type": "VariableDeclarator",
                  "start": 270,
                  "end": 306,
                  "loc": {
                    "start": {
                      "line": 13,
                      "column": 8
                    },
                    "end": {
                      "line": 13,
                      "column": 44
                    }
                  },
                  "id": {
                    "type": "ObjectPattern",
                    "start": 270,
                    "end": 298,
                    "loc": {
                      "start": {
                        "line": 13,
                        "column": 8
                      },
                      "end": {
                        "line": 13,
                        "column": 36
                      }
                    },
                    "properties": [
                      {
                        "type": "Property",
                        "start": 271,
                        "end": 275,
                        "loc": {
                          "start": {
                            "line": 13,
                            "column": 9
                          },
                          "end": {
                            "line": 13,
                            "column": 13
                          }
                        },
                        "method": false,
                        "shorthand": true,
                        "computed": false,
                        "key": {
                          "type": "Identifier",
                          "start": 271,
                          "end": 275,
                          "loc": {
                            "start": {
                              "line": 13,
                              "column": 9
                            },
                            "end": {
                              "line": 13,
                              "column": 13
                            }
                          },
                          "name": "size"
                        },
                        "kind": "init",
                        "value": {
                          "type": "Identifier",
                          "start": 271,
                          "end": 275,
                          "loc": {
                            "start": {
                              "line": 13,
                              "column": 9
                            },
                            "end": {
                              "line": 13,
                              "column": 13
                            }
                          },
                          "name": "size"
                        }
                      },
                      {
                        "type": "Property",
                        "start": 277,
                        "end": 286,
                        "loc": {
                          "start": {
                            "line": 13,
                            "column": 15
                          },
                          "end": {
                            "line": 13,
                            "column": 24
                          }
                        },
                        "method": false,
                        "shorthand": true,
                        "computed": false,
                        "key": {
                          "type": "Identifier",
                          "start": 277,
                          "end": 286,
                          "loc": {
                            "start": {
                              "line": 13,
                              "column": 15
                            },
                            "end": {
                              "line": 13,
                              "column": 24
                            }
                          },
                          "name": "className"
                        },
                        "kind": "init",
                        "value": {
                          "type": "Identifier",
                          "start": 277,
                          "end": 286,
                          "loc": {
                            "start": {
                              "line": 13,
                              "column": 15
                            },
                            "end": {
                              "line": 13,
                              "column": 24
                            }
                          },
                          "name": "className"
                        }
                      },
                      {
                        "type": "SpreadProperty",
                        "start": 288,
                        "end": 297,
                        "loc": {
                          "start": {
                            "line": 13,
                            "column": 26
                          },
                          "end": {
                            "line": 13,
                            "column": 35
                          }
                        },
                        "argument": {
                          "type": "Identifier",
                          "start": 291,
                          "end": 297,
                          "loc": {
                            "start": {
                              "line": 13,
                              "column": 29
                            },
                            "end": {
                              "line": 13,
                              "column": 35
                            }
                          },
                          "name": "others"
                        }
                      }
                    ]
                  },
                  "init": {
                    "type": "Identifier",
                    "start": 301,
                    "end": 306,
                    "loc": {
                      "start": {
                        "line": 13,
                        "column": 39
                      },
                      "end": {
                        "line": 13,
                        "column": 44
                      }
                    },
                    "name": "props"
                  }
                }
              ],
              "kind": "const"
            },
            {
              "type": "VariableDeclaration",
              "start": 310,
              "end": 371,
              "loc": {
                "start": {
                  "line": 14,
                  "column": 2
                },
                "end": {
                  "line": 14,
                  "column": 63
                }
              },
              "declarations": [
                {
                  "type": "VariableDeclarator",
                  "start": 314,
                  "end": 370,
                  "loc": {
                    "start": {
                      "line": 14,
                      "column": 6
                    },
                    "end": {
                      "line": 14,
                      "column": 62
                    }
                  },
                  "id": {
                    "type": "Identifier",
                    "start": 314,
                    "end": 321,
                    "loc": {
                      "start": {
                        "line": 14,
                        "column": 6
                      },
                      "end": {
                        "line": 14,
                        "column": 13
                      }
                    },
                    "name": "classes"
                  },
                  "init": {
                    "type": "CallExpression",
                    "start": 324,
                    "end": 370,
                    "loc": {
                      "start": {
                        "line": 14,
                        "column": 16
                      },
                      "end": {
                        "line": 14,
                        "column": 62
                      }
                    },
                    "callee": {
                      "type": "Identifier",
                      "start": 324,
                      "end": 334,
                      "loc": {
                        "start": {
                          "line": 14,
                          "column": 16
                        },
                        "end": {
                          "line": 14,
                          "column": 26
                        }
                      },
                      "name": "classNames"
                    },
                    "arguments": [
                      {
                        "type": "Literal",
                        "start": 335,
                        "end": 347,
                        "loc": {
                          "start": {
                            "line": 14,
                            "column": 27
                          },
                          "end": {
                            "line": 14,
                            "column": 39
                          }
                        },
                        "value": "icon-check",
                        "rawValue": "icon-check",
                        "raw": "'icon-check'"
                      },
                      {
                        "type": "ObjectExpression",
                        "start": 349,
                        "end": 369,
                        "loc": {
                          "start": {
                            "line": 14,
                            "column": 41
                          },
                          "end": {
                            "line": 14,
                            "column": 61
                          }
                        },
                        "properties": [
                          {
                            "type": "Property",
                            "start": 350,
                            "end": 368,
                            "loc": {
                              "start": {
                                "line": 14,
                                "column": 42
                              },
                              "end": {
                                "line": 14,
                                "column": 60
                              }
                            },
                            "method": false,
                            "shorthand": false,
                            "computed": false,
                            "key": {
                              "type": "Literal",
                              "start": 350,
                              "end": 357,
                              "loc": {
                                "start": {
                                  "line": 14,
                                  "column": 42
                                },
                                "end": {
                                  "line": 14,
                                  "column": 49
                                }
                              },
                              "value": "_user",
                              "rawValue": "_user",
                              "raw": "'_user'"
                            },
                            "value": {
                              "type": "Identifier",
                              "start": 359,
                              "end": 368,
                              "loc": {
                                "start": {
                                  "line": 14,
                                  "column": 51
                                },
                                "end": {
                                  "line": 14,
                                  "column": 60
                                }
                              },
                              "name": "className"
                            },
                            "kind": "init"
                          }
                        ]
                      }
                    ]
                  }
                }
              ],
              "kind": "let"
            },
            {
              "type": "VariableDeclaration",
              "start": 374,
              "end": 446,
              "loc": {
                "start": {
                  "line": 15,
                  "column": 2
                },
                "end": {
                  "line": 19,
                  "column": 4
                }
              },
              "declarations": [
                {
                  "type": "VariableDeclarator",
                  "start": 378,
                  "end": 445,
                  "loc": {
                    "start": {
                      "line": 15,
                      "column": 6
                    },
                    "end": {
                      "line": 19,
                      "column": 3
                    }
                  },
                  "id": {
                    "type": "Identifier",
                    "start": 378,
                    "end": 383,
                    "loc": {
                      "start": {
                        "line": 15,
                        "column": 6
                      },
                      "end": {
                        "line": 15,
                        "column": 11
                      }
                    },
                    "name": "style"
                  },
                  "init": {
                    "type": "ObjectExpression",
                    "start": 386,
                    "end": 445,
                    "loc": {
                      "start": {
                        "line": 15,
                        "column": 14
                      },
                      "end": {
                        "line": 19,
                        "column": 3
                      }
                    },
                    "properties": [
                      {
                        "type": "Property",
                        "start": 392,
                        "end": 404,
                        "loc": {
                          "start": {
                            "line": 16,
                            "column": 4
                          },
                          "end": {
                            "line": 16,
                            "column": 16
                          }
                        },
                        "method": false,
                        "shorthand": false,
                        "computed": false,
                        "key": {
                          "type": "Identifier",
                          "start": 392,
                          "end": 398,
                          "loc": {
                            "start": {
                              "line": 16,
                              "column": 4
                            },
                            "end": {
                              "line": 16,
                              "column": 10
                            }
                          },
                          "name": "height"
                        },
                        "value": {
                          "type": "Identifier",
                          "start": 400,
                          "end": 404,
                          "loc": {
                            "start": {
                              "line": 16,
                              "column": 12
                            },
                            "end": {
                              "line": 16,
                              "column": 16
                            }
                          },
                          "name": "size"
                        },
                        "kind": "init"
                      },
                      {
                        "type": "Property",
                        "start": 410,
                        "end": 421,
                        "loc": {
                          "start": {
                            "line": 17,
                            "column": 4
                          },
                          "end": {
                            "line": 17,
                            "column": 15
                          }
                        },
                        "method": false,
                        "shorthand": false,
                        "computed": false,
                        "key": {
                          "type": "Identifier",
                          "start": 410,
                          "end": 415,
                          "loc": {
                            "start": {
                              "line": 17,
                              "column": 4
                            },
                            "end": {
                              "line": 17,
                              "column": 9
                            }
                          },
                          "name": "width"
                        },
                        "value": {
                          "type": "Identifier",
                          "start": 417,
                          "end": 421,
                          "loc": {
                            "start": {
                              "line": 17,
                              "column": 11
                            },
                            "end": {
                              "line": 17,
                              "column": 15
                            }
                          },
                          "name": "size"
                        },
                        "kind": "init"
                      },
                      {
                        "type": "Property",
                        "start": 427,
                        "end": 441,
                        "loc": {
                          "start": {
                            "line": 18,
                            "column": 4
                          },
                          "end": {
                            "line": 18,
                            "column": 18
                          }
                        },
                        "method": false,
                        "shorthand": false,
                        "computed": false,
                        "key": {
                          "type": "Identifier",
                          "start": 427,
                          "end": 435,
                          "loc": {
                            "start": {
                              "line": 18,
                              "column": 4
                            },
                            "end": {
                              "line": 18,
                              "column": 12
                            }
                          },
                          "name": "fontSize"
                        },
                        "value": {
                          "type": "Identifier",
                          "start": 437,
                          "end": 441,
                          "loc": {
                            "start": {
                              "line": 18,
                              "column": 14
                            },
                            "end": {
                              "line": 18,
                              "column": 18
                            }
                          },
                          "name": "size"
                        },
                        "kind": "init"
                      }
                    ]
                  }
                }
              ],
              "kind": "let"
            },
            {
              "type": "ReturnStatement",
              "start": 450,
              "end": 519,
              "loc": {
                "start": {
                  "line": 21,
                  "column": 2
                },
                "end": {
                  "line": 23,
                  "column": 4
                }
              },
              "argument": {
                "type": "JSXElement",
                "start": 463,
                "end": 514,
                "loc": {
                  "start": {
                    "line": 22,
                    "column": 4
                  },
                  "end": {
                    "line": 22,
                    "column": 55
                  }
                },
                "openingElement": {
                  "type": "JSXOpeningElement",
                  "start": 463,
                  "end": 514,
                  "loc": {
                    "start": {
                      "line": 22,
                      "column": 4
                    },
                    "end": {
                      "line": 22,
                      "column": 55
                    }
                  },
                  "attributes": [
                    {
                      "type": "JSXAttribute",
                      "start": 466,
                      "end": 485,
                      "loc": {
                        "start": {
                          "line": 22,
                          "column": 7
                        },
                        "end": {
                          "line": 22,
                          "column": 26
                        }
                      },
                      "name": {
                        "type": "JSXIdentifier",
                        "start": 466,
                        "end": 475,
                        "loc": {
                          "start": {
                            "line": 22,
                            "column": 7
                          },
                          "end": {
                            "line": 22,
                            "column": 16
                          }
                        },
                        "name": "className"
                      },
                      "value": {
                        "type": "JSXExpressionContainer",
                        "start": 476,
                        "end": 485,
                        "loc": {
                          "start": {
                            "line": 22,
                            "column": 17
                          },
                          "end": {
                            "line": 22,
                            "column": 26
                          }
                        },
                        "expression": {
                          "type": "Identifier",
                          "start": 477,
                          "end": 484,
                          "loc": {
                            "start": {
                              "line": 22,
                              "column": 18
                            },
                            "end": {
                              "line": 22,
                              "column": 25
                            }
                          },
                          "name": "classes"
                        }
                      }
                    },
                    {
                      "type": "JSXAttribute",
                      "start": 486,
                      "end": 499,
                      "loc": {
                        "start": {
                          "line": 22,
                          "column": 27
                        },
                        "end": {
                          "line": 22,
                          "column": 40
                        }
                      },
                      "name": {
                        "type": "JSXIdentifier",
                        "start": 486,
                        "end": 491,
                        "loc": {
                          "start": {
                            "line": 22,
                            "column": 27
                          },
                          "end": {
                            "line": 22,
                            "column": 32
                          }
                        },
                        "name": "style"
                      },
                      "value": {
                        "type": "JSXExpressionContainer",
                        "start": 492,
                        "end": 499,
                        "loc": {
                          "start": {
                            "line": 22,
                            "column": 33
                          },
                          "end": {
                            "line": 22,
                            "column": 40
                          }
                        },
                        "expression": {
                          "type": "Identifier",
                          "start": 493,
                          "end": 498,
                          "loc": {
                            "start": {
                              "line": 22,
                              "column": 34
                            },
                            "end": {
                              "line": 22,
                              "column": 39
                            }
                          },
                          "name": "style"
                        }
                      }
                    },
                    {
                      "type": "JSXSpreadAttribute",
                      "start": 500,
                      "end": 511,
                      "loc": {
                        "start": {
                          "line": 22,
                          "column": 41
                        },
                        "end": {
                          "line": 22,
                          "column": 52
                        }
                      },
                      "argument": {
                        "type": "Identifier",
                        "start": 504,
                        "end": 510,
                        "loc": {
                          "start": {
                            "line": 22,
                            "column": 45
                          },
                          "end": {
                            "line": 22,
                            "column": 51
                          }
                        },
                        "name": "others"
                      }
                    }
                  ],
                  "name": {
                    "type": "JSXIdentifier",
                    "start": 464,
                    "end": 465,
                    "loc": {
                      "start": {
                        "line": 22,
                        "column": 5
                      },
                      "end": {
                        "line": 22,
                        "column": 6
                      }
                    },
                    "name": "i"
                  },
                  "selfClosing": true
                },
                "closingElement": null,
                "children": [],
                "parenthesizedExpression": true
              }
            }
          ],
          "trailingComments": null
        },
        "leadingComments": [
          {
            "type": "Block",
            "value": "*\n * 自定义 Icon\n * @param {object} props 传入组件的属性\n * @property {string} props.size 大小\n * @property {string} props.className 自定义 class\n ",
            "start": 82,
            "end": 218,
            "loc": {
              "start": {
                "line": 6,
                "column": 0
              },
              "end": {
                "line": 11,
                "column": 3
              }
            },
            "range": [
              82,
              218
            ]
          }
        ],
        "trailingComments": [
          {
            "type": "Block",
            "value": "*\n * 其他元素可以直接使用这个 class\n * @type {[type]}\n ",
            "start": 523,
            "end": 570,
            "loc": {
              "start": {
                "line": 26,
                "column": 0
              },
              "end": {
                "line": 29,
                "column": 3
              }
            },
            "range": [
              523,
              570
            ]
          }
        ]
      },
      "leadingComments": [
        {
          "type": "Block",
          "value": "*\n * 自定义 Icon\n * @param {object} props 传入组件的属性\n * @property {string} props.size 大小\n * @property {string} props.className 自定义 class\n ",
          "start": 82,
          "end": 218,
          "loc": {
            "start": {
              "line": 6,
              "column": 0
            },
            "end": {
              "line": 11,
              "column": 3
            }
          },
          "range": [
            82,
            218
          ]
        }
      ],
      "trailingComments": [
        {
          "type": "Block",
          "value": "*\n * 其他元素可以直接使用这个 class\n * @type {[type]}\n ",
          "start": 523,
          "end": 570,
          "loc": {
            "start": {
              "line": 26,
              "column": 0
            },
            "end": {
              "line": 29,
              "column": 3
            }
          },
          "range": [
            523,
            570
          ]
        }
      ]
    },
    {
      "type": "ExpressionStatement",
      "start": 571,
      "end": 618,
      "loc": {
        "start": {
          "line": 30,
          "column": 0
        },
        "end": {
          "line": 30,
          "column": 47
        }
      },
      "expression": {
        "type": "AssignmentExpression",
        "start": 571,
        "end": 617,
        "loc": {
          "start": {
            "line": 30,
            "column": 0
          },
          "end": {
            "line": 30,
            "column": 46
          }
        },
        "operator": "=",
        "left": {
          "type": "MemberExpression",
          "start": 571,
          "end": 590,
          "loc": {
            "start": {
              "line": 30,
              "column": 0
            },
            "end": {
              "line": 30,
              "column": 19
            }
          },
          "object": {
            "type": "Identifier",
            "start": 571,
            "end": 580,
            "loc": {
              "start": {
                "line": 30,
                "column": 0
              },
              "end": {
                "line": 30,
                "column": 9
              }
            },
            "name": "IconCheck",
            "leadingComments": null
          },
          "property": {
            "type": "Identifier",
            "start": 581,
            "end": 590,
            "loc": {
              "start": {
                "line": 30,
                "column": 10
              },
              "end": {
                "line": 30,
                "column": 19
              }
            },
            "name": "className"
          },
          "computed": false,
          "leadingComments": null
        },
        "right": {
          "type": "CallExpression",
          "start": 593,
          "end": 617,
          "loc": {
            "start": {
              "line": 30,
              "column": 22
            },
            "end": {
              "line": 30,
              "column": 46
            }
          },
          "callee": {
            "type": "Identifier",
            "start": 593,
            "end": 603,
            "loc": {
              "start": {
                "line": 30,
                "column": 22
              },
              "end": {
                "line": 30,
                "column": 32
              }
            },
            "name": "classNames"
          },
          "arguments": [
            {
              "type": "Literal",
              "start": 604,
              "end": 616,
              "loc": {
                "start": {
                  "line": 30,
                  "column": 33
                },
                "end": {
                  "line": 30,
                  "column": 45
                }
              },
              "value": "icon-check",
              "rawValue": "icon-check",
              "raw": "'icon-check'"
            }
          ]
        },
        "leadingComments": null
      },
      "leadingComments": [
        {
          "type": "Block",
          "value": "*\n * 其他元素可以直接使用这个 class\n * @type {[type]}\n ",
          "start": 523,
          "end": 570,
          "loc": {
            "start": {
              "line": 26,
              "column": 0
            },
            "end": {
              "line": 29,
              "column": 3
            }
          },
          "range": [
            523,
            570
          ]
        }
      ]
    },
    {
      "type": "ExpressionStatement",
      "start": 621,
      "end": 703,
      "loc": {
        "start": {
          "line": 33,
          "column": 0
        },
        "end": {
          "line": 36,
          "column": 2
        }
      },
      "expression": {
        "type": "AssignmentExpression",
        "start": 621,
        "end": 702,
        "loc": {
          "start": {
            "line": 33,
            "column": 0
          },
          "end": {
            "line": 36,
            "column": 1
          }
        },
        "operator": "=",
        "left": {
          "type": "MemberExpression",
          "start": 621,
          "end": 640,
          "loc": {
            "start": {
              "line": 33,
              "column": 0
            },
            "end": {
              "line": 33,
              "column": 19
            }
          },
          "object": {
            "type": "Identifier",
            "start": 621,
            "end": 630,
            "loc": {
              "start": {
                "line": 33,
                "column": 0
              },
              "end": {
                "line": 33,
                "column": 9
              }
            },
            "name": "IconCheck"
          },
          "property": {
            "type": "Identifier",
            "start": 631,
            "end": 640,
            "loc": {
              "start": {
                "line": 33,
                "column": 10
              },
              "end": {
                "line": 33,
                "column": 19
              }
            },
            "name": "propTypes"
          },
          "computed": false
        },
        "right": {
          "type": "ObjectExpression",
          "start": 643,
          "end": 702,
          "loc": {
            "start": {
              "line": 33,
              "column": 22
            },
            "end": {
              "line": 36,
              "column": 1
            }
          },
          "properties": [
            {
              "type": "Property",
              "start": 647,
              "end": 669,
              "loc": {
                "start": {
                  "line": 34,
                  "column": 2
                },
                "end": {
                  "line": 34,
                  "column": 24
                }
              },
              "method": false,
              "shorthand": false,
              "computed": false,
              "key": {
                "type": "Identifier",
                "start": 647,
                "end": 651,
                "loc": {
                  "start": {
                    "line": 34,
                    "column": 2
                  },
                  "end": {
                    "line": 34,
                    "column": 6
                  }
                },
                "name": "size"
              },
              "value": {
                "type": "MemberExpression",
                "start": 653,
                "end": 669,
                "loc": {
                  "start": {
                    "line": 34,
                    "column": 8
                  },
                  "end": {
                    "line": 34,
                    "column": 24
                  }
                },
                "object": {
                  "type": "Identifier",
                  "start": 653,
                  "end": 662,
                  "loc": {
                    "start": {
                      "line": 34,
                      "column": 8
                    },
                    "end": {
                      "line": 34,
                      "column": 17
                    }
                  },
                  "name": "PropTypes"
                },
                "property": {
                  "type": "Identifier",
                  "start": 663,
                  "end": 669,
                  "loc": {
                    "start": {
                      "line": 34,
                      "column": 18
                    },
                    "end": {
                      "line": 34,
                      "column": 24
                    }
                  },
                  "name": "string"
                },
                "computed": false
              },
              "kind": "init"
            },
            {
              "type": "Property",
              "start": 673,
              "end": 700,
              "loc": {
                "start": {
                  "line": 35,
                  "column": 2
                },
                "end": {
                  "line": 35,
                  "column": 29
                }
              },
              "method": false,
              "shorthand": false,
              "computed": false,
              "key": {
                "type": "Identifier",
                "start": 673,
                "end": 682,
                "loc": {
                  "start": {
                    "line": 35,
                    "column": 2
                  },
                  "end": {
                    "line": 35,
                    "column": 11
                  }
                },
                "name": "className"
              },
              "value": {
                "type": "MemberExpression",
                "start": 684,
                "end": 700,
                "loc": {
                  "start": {
                    "line": 35,
                    "column": 13
                  },
                  "end": {
                    "line": 35,
                    "column": 29
                  }
                },
                "object": {
                  "type": "Identifier",
                  "start": 684,
                  "end": 693,
                  "loc": {
                    "start": {
                      "line": 35,
                      "column": 13
                    },
                    "end": {
                      "line": 35,
                      "column": 22
                    }
                  },
                  "name": "PropTypes"
                },
                "property": {
                  "type": "Identifier",
                  "start": 694,
                  "end": 700,
                  "loc": {
                    "start": {
                      "line": 35,
                      "column": 23
                    },
                    "end": {
                      "line": 35,
                      "column": 29
                    }
                  },
                  "name": "string"
                },
                "computed": false
              },
              "kind": "init"
            }
          ]
        }
      }
    },
    {
      "type": "ExpressionStatement",
      "start": 705,
      "end": 749,
      "loc": {
        "start": {
          "line": 38,
          "column": 0
        },
        "end": {
          "line": 40,
          "column": 2
        }
      },
      "expression": {
        "type": "AssignmentExpression",
        "start": 705,
        "end": 748,
        "loc": {
          "start": {
            "line": 38,
            "column": 0
          },
          "end": {
            "line": 40,
            "column": 1
          }
        },
        "operator": "=",
        "left": {
          "type": "MemberExpression",
          "start": 705,
          "end": 727,
          "loc": {
            "start": {
              "line": 38,
              "column": 0
            },
            "end": {
              "line": 38,
              "column": 22
            }
          },
          "object": {
            "type": "Identifier",
            "start": 705,
            "end": 714,
            "loc": {
              "start": {
                "line": 38,
                "column": 0
              },
              "end": {
                "line": 38,
                "column": 9
              }
            },
            "name": "IconCheck"
          },
          "property": {
            "type": "Identifier",
            "start": 715,
            "end": 727,
            "loc": {
              "start": {
                "line": 38,
                "column": 10
              },
              "end": {
                "line": 38,
                "column": 22
              }
            },
            "name": "defaultProps"
          },
          "computed": false
        },
        "right": {
          "type": "ObjectExpression",
          "start": 730,
          "end": 748,
          "loc": {
            "start": {
              "line": 38,
              "column": 25
            },
            "end": {
              "line": 40,
              "column": 1
            }
          },
          "properties": [
            {
              "type": "Property",
              "start": 734,
              "end": 746,
              "loc": {
                "start": {
                  "line": 39,
                  "column": 2
                },
                "end": {
                  "line": 39,
                  "column": 14
                }
              },
              "method": false,
              "shorthand": false,
              "computed": false,
              "key": {
                "type": "Identifier",
                "start": 734,
                "end": 738,
                "loc": {
                  "start": {
                    "line": 39,
                    "column": 2
                  },
                  "end": {
                    "line": 39,
                    "column": 6
                  }
                },
                "name": "size"
              },
              "value": {
                "type": "Literal",
                "start": 740,
                "end": 746,
                "loc": {
                  "start": {
                    "line": 39,
                    "column": 8
                  },
                  "end": {
                    "line": 39,
                    "column": 14
                  }
                },
                "value": "40px",
                "rawValue": "40px",
                "raw": "'40px'"
              },
              "kind": "init"
            }
          ]
        }
      }
    }
  ]
}